{"name":"FootballR API","description":"Advanced API designed to provide accurate, real-time data on the world of football.","repoUrl":"https://github.com/mzafram2001/footballr-api","version":"v14072024","updated":"07.07.2024","message":"Created with love by Miguel Zafra.","competitions":[{"id":"PRL","name":"Premier League","description":"Premier League standings table, with detailed information.","yearStart":2024,"yearEnd":2025,"area":{"id":"j9N9ZNFA","name":"England","short":"ENG","color":"#DBDBDB"},"standings":[{"position":1,"team":{"id":"hA1Zm19f","name":"Arsenal","color":"#000000"},"playedGames":0,"wins":0,"draws":0,"loses":0,"goalsFor":0,"goalsAgainst":0,"goalDifference":0,"points":0,"form":"?"},{"position":2,"team":{"id":"W00wmLO0","name":"Aston Villa","color":"#000000"},"playedGames":0,"wins":0,"draws":0,"loses":0,"goalsFor":0,"goalsAgainst":0,"goalDifference":0,"points":0,"form":"?"},{"position":3,"team":{"id":"4fGZN2oK","name":"Chelsea","color":"#000000"},"playedGames":0,"wins":0,"draws":0,"loses":0,"goalsFor":0,"goalsAgainst":0,"goalDifference":0,"points":0,"form":"?"},{"position":4,"team":{"id":"KluSTr9s","name":"Everton","color":"#000000"},"playedGames":0,"wins":0,"draws":0,"loses":0,"goalsFor":0,"goalsAgainst":0,"goalDifference":0,"points":0,"form":"?"},{"position":5,"team":{"id":"69ZiU2Om","name":"Fulham","color":"#000000"},"playedGames":0,"wins":0,"draws":0,"loses":0,"goalsFor":0,"goalsAgainst":0,"goalDifference":0,"points":0,"form":"?"},{"position":6,"team":{"id":"lId4TMwf","name":"Liverpool","color":"#000000"},"playedGames":0,"wins":0,"draws":0,"loses":0,"goalsFor":0,"goalsAgainst":0,"goalDifference":0,"points":0,"form":"?"},{"position":7,"team":{"id":"Wtn9Stg0","name":"Manchester City","color":"#000000"},"playedGames":0,"wins":0,"draws":0,"loses":0,"goalsFor":0,"goalsAgainst":0,"goalDifference":0,"points":0,"form":"?"},{"position":8,"team":{"id":"ppjDR086","name":"Manchester Utd","color":"#000000"},"playedGames":0,"wins":0,"draws":0,"loses":0,"goalsFor":0,"goalsAgainst":0,"goalDifference":0,"points":0,"form":"?"},{"position":9,"team":{"id":"p6ahwuwJ","name":"Newcastle","color":"#000000"},"playedGames":0,"wins":0,"draws":0,"loses":0,"goalsFor":0,"goalsAgainst":0,"goalDifference":0,"points":0,"form":"?"},{"position":10,"team":{"id":"UDg08Ohm","name":"Tottenham","color":"#000000"},"playedGames":0,"wins":0,"draws":0,"loses":0,"goalsFor":0,"goalsAgainst":0,"goalDifference":0,"points":0,"form":"?"},{"position":11,"team":{"id":"Cxq57r8g","name":"West Ham","color":"#000000"},"playedGames":0,"wins":0,"draws":0,"loses":0,"goalsFor":0,"goalsAgainst":0,"goalDifference":0,"points":0,"form":"?"},{"position":12,"team":{"id":"AovF1Mia","name":"Crystal Palace","color":"#000000"},"playedGames":0,"wins":0,"draws":0,"loses":0,"goalsFor":0,"goalsAgainst":0,"goalDifference":0,"points":0,"form":"?"},{"position":13,"team":{"id":"thqhB2MB","name":"Ipswich","color":"#000000"},"playedGames":0,"wins":0,"draws":0,"loses":0,"goalsFor":0,"goalsAgainst":0,"goalDifference":0,"points":0,"form":"?"},{"position":14,"team":{"id":"KrrdAMyI","name":"Leicester","color":"#000000"},"playedGames":0,"wins":0,"draws":0,"loses":0,"goalsFor":0,"goalsAgainst":0,"goalDifference":0,"points":0,"form":"?"},{"position":15,"team":{"id":"WdKOwxDM","name":"Southampton","color":"#000000"},"playedGames":0,"wins":0,"draws":0,"loses":0,"goalsFor":0,"goalsAgainst":0,"goalDifference":0,"points":0,"form":"?"},{"position":16,"team":{"id":"j3Azpf5d","name":"Wolves","color":"#000000"},"playedGames":0,"wins":0,"draws":0,"loses":0,"goalsFor":0,"goalsAgainst":0,"goalDifference":0,"points":0,"form":"?"},{"position":17,"team":{"id":"OtpNdwrc","name":"Bournemouth","color":"#000000"},"playedGames":0,"wins":0,"draws":0,"loses":0,"goalsFor":0,"goalsAgainst":0,"goalDifference":0,"points":0,"form":"?"},{"position":18,"team":{"id":"2XrRecc3","name":"Brighton","color":"#000000"},"playedGames":0,"wins":0,"draws":0,"loses":0,"goalsFor":0,"goalsAgainst":0,"goalDifference":0,"points":0,"form":"?"},{"position":19,"team":{"id":"UsushcZr","name":"Nottingham","color":"#000000"},"playedGames":0,"wins":0,"draws":0,"loses":0,"goalsFor":0,"goalsAgainst":0,"goalDifference":0,"points":0,"form":"?"},{"position":20,"team":{"id":"xYe7DwID","name":"Brentford","color":"#000000"},"playedGames":0,"wins":0,"draws":0,"loses":0,"goalsFor":0,"goalsAgainst":0,"goalDifference":0,"points":0,"form":"?"}]}]}