{"standings":[{"position":"1","team":{"id":"SKbpVP5K","name":"Barcelona","short":"BAR","color":"#A50044"},"playedGames":"18","wins":"12","draws":"2","losses":"4","goalsFor":"50","goalsAgainst":"20","goalsDifference":"30","points":"38","form":"L,D,W,L,D"},{"position":"2","team":{"id":"jaarqpLQ","name":"Atlético Madrid","short":"ATM","color":"#CB3524"},"playedGames":"17","wins":"11","draws":"5","losses":"1","goalsFor":"31","goalsAgainst":"11","goalsDifference":"20","points":"38","form":"W,W,W,W,W"},{"position":"3","team":{"id":"W8mj7MDD","name":"Real Madrid","short":"RMA","color":"#FCF7F7"},"playedGames":"17","wins":"11","draws":"4","losses":"2","goalsFor":"37","goalsAgainst":"16","goalsDifference":"21","points":"37","form":"D,W,L,W,W"},{"position":"4","team":{"id":"IP5zl0cJ","name":"Athletic Bilbao","short":"BIL","color":"#B0B0B0"},"playedGames":"18","wins":"9","draws":"6","losses":"3","goalsFor":"27","goalsAgainst":"16","goalsDifference":"11","points":"33","form":"D,W,W,W,W"},{"position":"5","team":{"id":"lUatW5jE","name":"Villarreal","short":"VIL","color":"#FFE667"},"playedGames":"17","wins":"7","draws":"6","losses":"4","goalsFor":"29","goalsAgainst":"28","goalsDifference":"1","points":"27","form":"D,L,L,D,D"},{"position":"6","team":{"id":"4jDQxrbf","name":"Mallorca","short":"MAL","color":"#7A0404"},"playedGames":"18","wins":"8","draws":"3","losses":"7","goalsFor":"18","goalsAgainst":"21","goalsDifference":"-3","points":"27","form":"W,L,L,W,W"},{"position":"7","team":{"id":"jNvak2f3","name":"Real Sociedad","short":"RSO","color":"#446175"},"playedGames":"17","wins":"7","draws":"4","losses":"6","goalsFor":"16","goalsAgainst":"11","goalsDifference":"5","points":"25","form":"D,W,W,L,W"},{"position":"8","team":{"id":"ETdxjU8a","name":"Osasuna","short":"OSA","color":"#D91A21"},"playedGames":"17","wins":"6","draws":"7","losses":"4","goalsFor":"22","goalsAgainst":"25","goalsDifference":"-3","points":"25","form":"D,D,D,D,L"},{"position":"9","team":{"id":"vJbTeCGP","name":"Real Betis","short":"BET","color":"#25961D"},"playedGames":"17","wins":"6","draws":"6","losses":"5","goalsFor":"20","goalsAgainst":"21","goalsDifference":"-1","points":"24","form":"W,D,L,L,D"},{"position":"10","team":{"id":"nNNpcUSL","name":"Girona","short":"GIR","color":"#BD3541"},"playedGames":"17","wins":"6","draws":"4","losses":"7","goalsFor":"23","goalsAgainst":"25","goalsDifference":"-2","points":"22","form":"L,L,D,W,W"},{"position":"11","team":{"id":"h8oAv4Ts","name":"Sevilla","short":"SEV","color":"#FAFAFA"},"playedGames":"17","wins":"6","draws":"4","losses":"7","goalsFor":"18","goalsAgainst":"23","goalsDifference":"-5","points":"22","form":"W,L,D,W,L"},{"position":"12","team":{"id":"8bcjFy6O","name":"Rayo Vallecano","short":"RAY","color":"#333333"},"playedGames":"17","wins":"5","draws":"6","losses":"6","goalsFor":"19","goalsAgainst":"20","goalsDifference":"-1","points":"21","form":"D,D,W,L,L"},{"position":"13","team":{"id":"8pvUZFhf","name":"Celta Vigo","short":"CEL","color":"#8ABDFF"},"playedGames":"17","wins":"6","draws":"3","losses":"8","goalsFor":"25","goalsAgainst":"28","goalsDifference":"-3","points":"21","form":"L,W,L,D,D"},{"position":"14","team":{"id":"IyRQC2vM","name":"Las Palmas","short":"PAL","color":"#FFE400"},"playedGames":"17","wins":"5","draws":"4","losses":"8","goalsFor":"22","goalsAgainst":"27","goalsDifference":"-5","points":"19","form":"D,W,W,L,W"},{"position":"15","team":{"id":"Mi0rXQg7","name":"Leganés","short":"LEG","color":"#DBB731"},"playedGames":"17","wins":"4","draws":"6","losses":"7","goalsFor":"15","goalsAgainst":"23","goalsDifference":"-8","points":"18","form":"W,L,D,L,W"},{"position":"16","team":{"id":"dboeiWOt","name":"Getafe","short":"GET","color":"#005999"},"playedGames":"17","wins":"3","draws":"7","losses":"7","goalsFor":"11","goalsAgainst":"14","goalsDifference":"-3","points":"16","form":"L,W,L,W,L"},{"position":"17","team":{"id":"hxt57t2q","name":"Alavés","short":"ALA","color":"#0232A0"},"playedGames":"17","wins":"4","draws":"4","losses":"9","goalsFor":"19","goalsAgainst":"28","goalsDifference":"-9","points":"16","form":"D,D,D,L,L"},{"position":"18","team":{"id":"QFfPdh1J","name":"Espanyol","short":"ESP","color":"#0587D1"},"playedGames":"17","wins":"4","draws":"3","losses":"10","goalsFor":"16","goalsAgainst":"29","goalsDifference":"-13","points":"15","form":"D,D,L,W,L"},{"position":"19","team":{"id":"zkpajjvm","name":"Valladolid","short":"VLL","color":"#3D1169"},"playedGames":"17","wins":"3","draws":"3","losses":"11","goalsFor":"12","goalsAgainst":"34","goalsDifference":"-22","points":"12","form":"W,L,L,L,D"},{"position":"20","team":{"id":"CQeaytrD","name":"Valencia","short":"VAL","color":"#FF8308"},"playedGames":"16","wins":"2","draws":"5","losses":"9","goalsFor":"14","goalsAgainst":"24","goalsDifference":"-10","points":"11","form":"D,L,L,L,W"}]}