{"name":"Premier League","area":"ENG","yearStart":2023,"yearEnd":2024,"standings":[{"position":1,"team":{"id":"p6ahwuwJ","name":"Newcastle United","logo":"https://raw.githubusercontent.com/mzafram2001/zeus-src/main/static/teams/p6ahwuwJ.svg"},"playedGames":1,"wins":1,"draws":0,"loses":0,"goalsFor":5,"goalsAgainst":1,"goalDifference":4,"points":3,"form":"W"},{"position":2,"team":{"id":"2XrRecc3","name":"Brighton","logo":"https://raw.githubusercontent.com/mzafram2001/zeus-src/main/static/teams/2XrRecc3.svg"},"playedGames":1,"wins":1,"draws":0,"loses":0,"goalsFor":4,"goalsAgainst":1,"goalDifference":3,"points":3,"form":"W"},{"position":3,"team":{"id":"Wtn9Stg0","name":"Manchester City","logo":"https://raw.githubusercontent.com/mzafram2001/zeus-src/main/static/teams/Wtn9Stg0.svg"},"playedGames":1,"wins":1,"draws":0,"loses":0,"goalsFor":3,"goalsAgainst":0,"goalDifference":3,"points":3,"form":"W"},{"position":4,"team":{"id":"hA1Zm19f","name":"Arsenal","logo":"https://raw.githubusercontent.com/mzafram2001/zeus-src/main/static/teams/hA1Zm19f.svg"},"playedGames":1,"wins":1,"draws":0,"loses":0,"goalsFor":2,"goalsAgainst":1,"goalDifference":1,"points":3,"form":"W"},{"position":5,"team":{"id":"69ZiU2Om","name":"Fulham","logo":"https://raw.githubusercontent.com/mzafram2001/zeus-src/main/static/teams/69ZiU2Om.svg"},"playedGames":1,"wins":1,"draws":0,"loses":0,"goalsFor":1,"goalsAgainst":0,"goalDifference":1,"points":3,"form":"W"},{"position":6,"team":{"id":"ppjDR086","name":"Manchester United","logo":"https://raw.githubusercontent.com/mzafram2001/zeus-src/main/static/teams/ppjDR086.svg"},"playedGames":1,"wins":1,"draws":0,"loses":0,"goalsFor":1,"goalsAgainst":0,"goalDifference":1,"points":3,"form":"W"},{"position":7,"team":{"id":"AovF1Mia","name":"Crystal Palace","logo":"https://raw.githubusercontent.com/mzafram2001/zeus-src/main/static/teams/AovF1Mia.svg"},"playedGames":1,"wins":1,"draws":0,"loses":0,"goalsFor":1,"goalsAgainst":0,"goalDifference":1,"points":3,"form":"W"},{"position":8,"team":{"id":"UsushcZr","name":"Nottingham Forest","logo":"https://raw.githubusercontent.com/mzafram2001/zeus-src/main/static/teams/UsushcZr.svg"},"playedGames":2,"wins":1,"draws":0,"loses":1,"goalsFor":3,"goalsAgainst":3,"goalDifference":0,"points":3,"form":"W,L"},{"position":9,"team":{"id":"UDg08Ohm","name":"Tottenham Hotspur","logo":"https://raw.githubusercontent.com/mzafram2001/zeus-src/main/static/teams/UDg08Ohm.svg"},"playedGames":1,"wins":0,"draws":1,"loses":0,"goalsFor":2,"goalsAgainst":2,"goalDifference":0,"points":1,"form":"D"},{"position":10,"team":{"id":"xYe7DwID","name":"Brentford","logo":"https://raw.githubusercontent.com/mzafram2001/zeus-src/main/static/teams/xYe7DwID.svg"},"playedGames":1,"wins":0,"draws":1,"loses":0,"goalsFor":2,"goalsAgainst":2,"goalDifference":0,"points":1,"form":"D"},{"position":11,"team":{"id":"4fGZN2oK","name":"Chelsea","logo":"https://raw.githubusercontent.com/mzafram2001/zeus-src/main/static/teams/4fGZN2oK.svg"},"playedGames":1,"wins":0,"draws":1,"loses":0,"goalsFor":1,"goalsAgainst":1,"goalDifference":0,"points":1,"form":"D"},{"position":12,"team":{"id":"lId4TMwf","name":"Liverpool","logo":"https://raw.githubusercontent.com/mzafram2001/zeus-src/main/static/teams/lId4TMwf.svg"},"playedGames":1,"wins":0,"draws":1,"loses":0,"goalsFor":1,"goalsAgainst":1,"goalDifference":0,"points":1,"form":"D"},{"position":13,"team":{"id":"Cxq57r8g","name":"West Ham United","logo":"https://raw.githubusercontent.com/mzafram2001/zeus-src/main/static/teams/Cxq57r8g.svg"},"playedGames":1,"wins":0,"draws":1,"loses":0,"goalsFor":1,"goalsAgainst":1,"goalDifference":0,"points":1,"form":"D"},{"position":14,"team":{"id":"OtpNdwrc","name":"Athletic Bournemouth","logo":"https://raw.githubusercontent.com/mzafram2001/zeus-src/main/static/teams/OtpNdwrc.svg"},"playedGames":1,"wins":0,"draws":1,"loses":0,"goalsFor":1,"goalsAgainst":1,"goalDifference":0,"points":1,"form":"D"},{"position":15,"team":{"id":"KluSTr9s","name":"Everton","logo":"https://raw.githubusercontent.com/mzafram2001/zeus-src/main/static/teams/KluSTr9s.svg"},"playedGames":1,"wins":0,"draws":0,"loses":1,"goalsFor":0,"goalsAgainst":1,"goalDifference":-1,"points":0,"form":"L"},{"position":16,"team":{"id":"j3Azpf5d","name":"Wolverhampton Wanderers","logo":"https://raw.githubusercontent.com/mzafram2001/zeus-src/main/static/teams/j3Azpf5d.svg"},"playedGames":1,"wins":0,"draws":0,"loses":1,"goalsFor":0,"goalsAgainst":1,"goalDifference":-1,"points":0,"form":"L"},{"position":17,"team":{"id":"MeKPSerA","name":"Sheffield United","logo":"https://raw.githubusercontent.com/mzafram2001/zeus-src/main/static/teams/MeKPSerA.svg"},"playedGames":2,"wins":0,"draws":0,"loses":2,"goalsFor":1,"goalsAgainst":3,"goalDifference":-2,"points":0,"form":"L,L"},{"position":18,"team":{"id":"SlybbadF","name":"Luton","logo":"https://raw.githubusercontent.com/mzafram2001/zeus-src/main/static/teams/SlybbadF.svg"},"playedGames":1,"wins":0,"draws":0,"loses":1,"goalsFor":1,"goalsAgainst":4,"goalDifference":-3,"points":0,"form":"L"},{"position":19,"team":{"id":"z3dmTMMO","name":"Burnley","logo":"https://raw.githubusercontent.com/mzafram2001/zeus-src/main/static/teams/z3dmTMMO.svg"},"playedGames":1,"wins":0,"draws":0,"loses":1,"goalsFor":0,"goalsAgainst":3,"goalDifference":-3,"points":0,"form":"L"},{"position":20,"team":{"id":"W00wmLO0","name":"Aston Villa","logo":"https://raw.githubusercontent.com/mzafram2001/zeus-src/main/static/teams/W00wmLO0.svg"},"playedGames":1,"wins":0,"draws":0,"loses":1,"goalsFor":1,"goalsAgainst":5,"goalDifference":-4,"points":0,"form":"L"}]}