{"name":"LaLiga","area":"ESP","yearStart":2023,"yearEnd":2024,"standings":[{"position":1,"team":{"id":"8bcjFy6O","name":"Rayo Vallecano","logo":"https://raw.githubusercontent.com/mzafram2001/zeus-src/main/static/teams/8bcjFy6O.svg"},"playedGames":1,"wins":1,"draws":0,"loses":0,"goalsFor":2,"goalsAgainst":0,"goalDifference":2,"points":3,"form":"W"},{"position":2,"team":{"id":"W8mj7MDD","name":"Real Madrid","logo":"https://raw.githubusercontent.com/mzafram2001/zeus-src/main/static/teams/W8mj7MDD.svg"},"playedGames":1,"wins":1,"draws":0,"loses":0,"goalsFor":2,"goalsAgainst":0,"goalDifference":2,"points":3,"form":"W"},{"position":3,"team":{"id":"CQeaytrD","name":"Valencia","logo":"https://raw.githubusercontent.com/mzafram2001/zeus-src/main/static/teams/CQeaytrD.svg"},"playedGames":1,"wins":1,"draws":0,"loses":0,"goalsFor":2,"goalsAgainst":1,"goalDifference":1,"points":3,"form":"W"},{"position":4,"team":{"id":"jNvak2f3","name":"Real Sociedad","logo":"https://raw.githubusercontent.com/mzafram2001/zeus-src/main/static/teams/jNvak2f3.svg"},"playedGames":1,"wins":0,"draws":1,"loses":0,"goalsFor":1,"goalsAgainst":1,"goalDifference":0,"points":1,"form":"D"},{"position":5,"team":{"id":"IyRQC2vM","name":"Las Palmas","logo":"https://raw.githubusercontent.com/mzafram2001/zeus-src/main/static/teams/IyRQC2vM.svg"},"playedGames":1,"wins":0,"draws":1,"loses":0,"goalsFor":1,"goalsAgainst":1,"goalDifference":0,"points":1,"form":"D"},{"position":6,"team":{"id":"4jDQxrbf","name":"Mallorca","logo":"https://raw.githubusercontent.com/mzafram2001/zeus-src/main/static/teams/4jDQxrbf.svg"},"playedGames":1,"wins":0,"draws":1,"loses":0,"goalsFor":1,"goalsAgainst":1,"goalDifference":0,"points":1,"form":"D"},{"position":7,"team":{"id":"nNNpcUSL","name":"Girona","logo":"https://raw.githubusercontent.com/mzafram2001/zeus-src/main/static/teams/nNNpcUSL.svg"},"playedGames":1,"wins":0,"draws":1,"loses":0,"goalsFor":1,"goalsAgainst":1,"goalDifference":0,"points":1,"form":"D"},{"position":8,"team":{"id":"hxt57t2q","name":"Deportivo Alavés","logo":"https://raw.githubusercontent.com/mzafram2001/zeus-src/main/static/teams/hxt57t2q.svg"},"playedGames":0,"wins":0,"draws":0,"loses":0,"goalsFor":0,"goalsAgainst":0,"goalDifference":0,"points":0,"form":"-"},{"position":9,"team":{"id":"8pvUZFhf","name":"Celta Vigo","logo":"https://raw.githubusercontent.com/mzafram2001/zeus-src/main/static/teams/8pvUZFhf.svg"},"playedGames":0,"wins":0,"draws":0,"loses":0,"goalsFor":0,"goalsAgainst":0,"goalDifference":0,"points":0,"form":"-"},{"position":10,"team":{"id":"hdWjLJUJ","name":"Cádiz","logo":"https://raw.githubusercontent.com/mzafram2001/zeus-src/main/static/teams/hdWjLJUJ.svg"},"playedGames":0,"wins":0,"draws":0,"loses":0,"goalsFor":0,"goalsAgainst":0,"goalDifference":0,"points":0,"form":"-"},{"position":11,"team":{"id":"lUatW5jE","name":"Villarreal","logo":"https://raw.githubusercontent.com/mzafram2001/zeus-src/main/static/teams/lUatW5jE.svg"},"playedGames":0,"wins":0,"draws":0,"loses":0,"goalsFor":0,"goalsAgainst":0,"goalDifference":0,"points":0,"form":"-"},{"position":12,"team":{"id":"SKbpVP5K","name":"Barcelona","logo":"https://raw.githubusercontent.com/mzafram2001/zeus-src/main/static/teams/SKbpVP5K.svg"},"playedGames":0,"wins":0,"draws":0,"loses":0,"goalsFor":0,"goalsAgainst":0,"goalDifference":0,"points":0,"form":"-"},{"position":13,"team":{"id":"jaarqpLQ","name":"Atlético Madrid","logo":"https://raw.githubusercontent.com/mzafram2001/zeus-src/main/static/teams/jaarqpLQ.svg"},"playedGames":0,"wins":0,"draws":0,"loses":0,"goalsFor":0,"goalsAgainst":0,"goalDifference":0,"points":0,"form":"-"},{"position":14,"team":{"id":"vJbTeCGP","name":"Real Betis","logo":"https://raw.githubusercontent.com/mzafram2001/zeus-src/main/static/teams/vJbTeCGP.svg"},"playedGames":0,"wins":0,"draws":0,"loses":0,"goalsFor":0,"goalsAgainst":0,"goalDifference":0,"points":0,"form":"-"},{"position":15,"team":{"id":"dboeiWOt","name":"Getafe","logo":"https://raw.githubusercontent.com/mzafram2001/zeus-src/main/static/teams/dboeiWOt.svg"},"playedGames":0,"wins":0,"draws":0,"loses":0,"goalsFor":0,"goalsAgainst":0,"goalDifference":0,"points":0,"form":"-"},{"position":16,"team":{"id":"ETdxjU8a","name":"Osasuna","logo":"https://raw.githubusercontent.com/mzafram2001/zeus-src/main/static/teams/ETdxjU8a.svg"},"playedGames":0,"wins":0,"draws":0,"loses":0,"goalsFor":0,"goalsAgainst":0,"goalDifference":0,"points":0,"form":"-"},{"position":17,"team":{"id":"EXuxl1xP","name":"Granada","logo":"https://raw.githubusercontent.com/mzafram2001/zeus-src/main/static/teams/EXuxl1xP.svg"},"playedGames":0,"wins":0,"draws":0,"loses":0,"goalsFor":0,"goalsAgainst":0,"goalDifference":0,"points":0,"form":"-"},{"position":18,"team":{"id":"h8oAv4Ts","name":"Sevilla","logo":"https://raw.githubusercontent.com/mzafram2001/zeus-src/main/static/teams/h8oAv4Ts.svg"},"playedGames":1,"wins":0,"draws":0,"loses":1,"goalsFor":1,"goalsAgainst":2,"goalDifference":-1,"points":0,"form":"L"},{"position":19,"team":{"id":"nF2Vy2D0","name":"Almería","logo":"https://raw.githubusercontent.com/mzafram2001/zeus-src/main/static/teams/nF2Vy2D0.svg"},"playedGames":1,"wins":0,"draws":0,"loses":1,"goalsFor":0,"goalsAgainst":2,"goalDifference":-2,"points":0,"form":"L"},{"position":20,"team":{"id":"IP5zl0cJ","name":"Athletic Bilbao","logo":"https://raw.githubusercontent.com/mzafram2001/zeus-src/main/static/teams/IP5zl0cJ.svg"},"playedGames":1,"wins":0,"draws":0,"loses":1,"goalsFor":0,"goalsAgainst":2,"goalDifference":-2,"points":0,"form":"L"}]}