{"name":"LaLiga","area":"ESP","yearStart":2023,"yearEnd":2024,"scorers":[{"position":1,"player":{"id":"MVC8zHZD","name":"Robert Lewandowski"},"team":{"id":"SKbpVP5K","name":"Barcelona","logo":"https://raw.githubusercontent.com/mzafram2001/zeus-src/main/static/teams/SKbpVP5K.svg"},"area":{"id":"POL","name":"Poland","flag":"https://raw.githubusercontent.com/mzafram2001/zeus-src/main/static/flags/2HzmcynI.svg"},"goals":5,"assists":3},{"position":2,"player":{"id":"QNvlPm7s","name":"Jude Bellingham"},"team":{"id":"W8mj7MDD","name":"Real Madrid","logo":"https://raw.githubusercontent.com/mzafram2001/zeus-src/main/static/teams/W8mj7MDD.svg"},"area":{"id":"ENG","name":"England","flag":"https://raw.githubusercontent.com/mzafram2001/zeus-src/main/static/flags/j9N9ZNFA.svg"},"goals":5,"assists":1},{"position":3,"player":{"id":"fmkHs3aU","name":"Alvaro Morata"},"team":{"id":"jaarqpLQ","name":"Atlético Madrid","logo":"https://raw.githubusercontent.com/mzafram2001/zeus-src/main/static/teams/jaarqpLQ.svg"},"area":{"id":"ESP","name":"Spain","flag":"https://raw.githubusercontent.com/mzafram2001/zeus-src/main/static/flags/bLyo6mco.svg"},"goals":5,"assists":0},{"position":4,"player":{"id":"W4HzaGVn","name":"Inaki Williams"},"team":{"id":"IP5zl0cJ","name":"Athletic Bilbao","logo":"https://raw.githubusercontent.com/mzafram2001/zeus-src/main/static/teams/IP5zl0cJ.svg"},"area":{"id":"-","name":"-","flag":"-"},"goals":4,"assists":2},{"position":5,"player":{"id":"fqdLdpc3","name":"Takefusa Kubo"},"team":{"id":"jNvak2f3","name":"Real Sociedad","logo":"https://raw.githubusercontent.com/mzafram2001/zeus-src/main/static/teams/jNvak2f3.svg"},"area":{"id":"JPN","name":"Japan","flag":"https://raw.githubusercontent.com/mzafram2001/zeus-src/main/static/flags/ULXPdOUj.svg"},"goals":4,"assists":1},{"position":6,"player":{"id":"GIzJfhLr","name":"Sergio Arribas"},"team":{"id":"nF2Vy2D0","name":"Almería","logo":"https://raw.githubusercontent.com/mzafram2001/zeus-src/main/static/teams/nF2Vy2D0.svg"},"area":{"id":"ESP","name":"Spain","flag":"https://raw.githubusercontent.com/mzafram2001/zeus-src/main/static/flags/bLyo6mco.svg"},"goals":4,"assists":0},{"position":7,"player":{"id":"zB1s0lKl","name":"Abdon Prats"},"team":{"id":"4jDQxrbf","name":"Mallorca","logo":"https://raw.githubusercontent.com/mzafram2001/zeus-src/main/static/teams/4jDQxrbf.svg"},"area":{"id":"ESP","name":"Spain","flag":"https://raw.githubusercontent.com/mzafram2001/zeus-src/main/static/flags/bLyo6mco.svg"},"goals":4,"assists":0},{"position":8,"player":{"id":"QwqgNkTP","name":"Alexander Sorloth"},"team":{"id":"lUatW5jE","name":"Villarreal","logo":"https://raw.githubusercontent.com/mzafram2001/zeus-src/main/static/teams/lUatW5jE.svg"},"area":{"id":"NOR","name":"Norway","flag":"https://raw.githubusercontent.com/mzafram2001/zeus-src/main/static/flags/8rP6JO0H.svg"},"goals":4,"assists":0},{"position":9,"player":{"id":"C63L6vqA","name":"Artem Dovbyk"},"team":{"id":"nNNpcUSL","name":"Girona","logo":"https://raw.githubusercontent.com/mzafram2001/zeus-src/main/static/teams/nNNpcUSL.svg"},"area":{"id":"UKR","name":"Ukraine","flag":"https://raw.githubusercontent.com/mzafram2001/zeus-src/main/static/flags/j1JtDMwo.svg"},"goals":3,"assists":2},{"position":10,"player":{"id":"EP4vWYSf","name":"Hugo Duro"},"team":{"id":"CQeaytrD","name":"Valencia","logo":"https://raw.githubusercontent.com/mzafram2001/zeus-src/main/static/teams/CQeaytrD.svg"},"area":{"id":"ESP","name":"Spain","flag":"https://raw.githubusercontent.com/mzafram2001/zeus-src/main/static/flags/bLyo6mco.svg"},"goals":3,"assists":1}]}