{"name":"Serie A","area":"ITA","yearStart":2017,"yearEnd":2018,"standings":[{"position":1,"team":{"id":"C06aJvIB","name":"Juventus","logo":"https://raw.githubusercontent.com/mzafram2001/zeus-src/main/static/logos/C06aJvIB_logo.png","kit":"https://raw.githubusercontent.com/mzafram2001/zeus-src/main/static/kits/C06aJvIB_kit.png"},"playedGames":38,"wins":30,"draws":5,"loses":3,"goalsFor":86,"goalsAgainst":24,"goalDifference":62,"points":95,"form":"W,D,W,W,L"},{"position":2,"team":{"id":"69Dxbc61","name":"Napoli","logo":"https://raw.githubusercontent.com/mzafram2001/zeus-src/main/static/logos/69Dxbc61_logo.png","kit":"https://raw.githubusercontent.com/mzafram2001/zeus-src/main/static/kits/69Dxbc61_kit.png"},"playedGames":38,"wins":28,"draws":7,"loses":3,"goalsFor":77,"goalsAgainst":29,"goalDifference":48,"points":91,"form":"W,W,D,L,W"},{"position":3,"team":{"id":"zVqqL0ma","name":"AS Roma","logo":"https://raw.githubusercontent.com/mzafram2001/zeus-src/main/static/logos/zVqqL0ma_logo.png","kit":"https://raw.githubusercontent.com/mzafram2001/zeus-src/main/static/kits/zVqqL0ma_kit.png"},"playedGames":38,"wins":23,"draws":8,"loses":7,"goalsFor":61,"goalsAgainst":28,"goalDifference":33,"points":77,"form":"W,D,W,W,W"},{"position":4,"team":{"id":"Iw7eKK25","name":"Inter","logo":"https://raw.githubusercontent.com/mzafram2001/zeus-src/main/static/logos/Iw7eKK25_logo.png","kit":"https://raw.githubusercontent.com/mzafram2001/zeus-src/main/static/kits/Iw7eKK25_kit.png"},"playedGames":38,"wins":20,"draws":12,"loses":6,"goalsFor":66,"goalsAgainst":30,"goalDifference":36,"points":72,"form":"W,L,W,L,W"},{"position":5,"team":{"id":"URcSl02h","name":"Lazio","logo":"https://raw.githubusercontent.com/mzafram2001/zeus-src/main/static/logos/URcSl02h_logo.png","kit":"https://raw.githubusercontent.com/mzafram2001/zeus-src/main/static/kits/URcSl02h_kit.png"},"playedGames":38,"wins":21,"draws":9,"loses":8,"goalsFor":89,"goalsAgainst":49,"goalDifference":40,"points":72,"form":"L,D,D,W,W"},{"position":6,"team":{"id":"8Sa8HInO","name":"AC Milan","logo":"https://raw.githubusercontent.com/mzafram2001/zeus-src/main/static/logos/8Sa8HInO_logo.png","kit":"https://raw.githubusercontent.com/mzafram2001/zeus-src/main/static/kits/8Sa8HInO_kit.png"},"playedGames":38,"wins":18,"draws":10,"loses":10,"goalsFor":56,"goalsAgainst":42,"goalDifference":14,"points":64,"form":"W,D,W,W,L"},{"position":7,"team":{"id":"8C9JjMXu","name":"Atalanta","logo":"https://raw.githubusercontent.com/mzafram2001/zeus-src/main/static/logos/8C9JjMXu_logo.png","kit":"https://raw.githubusercontent.com/mzafram2001/zeus-src/main/static/kits/8C9JjMXu_kit.png"},"playedGames":38,"wins":16,"draws":12,"loses":10,"goalsFor":57,"goalsAgainst":39,"goalDifference":18,"points":60,"form":"L,D,D,W,W"},{"position":8,"team":{"id":"Q3A3IbXH","name":"Fiorentina","logo":"https://raw.githubusercontent.com/mzafram2001/zeus-src/main/static/logos/Q3A3IbXH_logo.png","kit":"https://raw.githubusercontent.com/mzafram2001/zeus-src/main/static/kits/Q3A3IbXH_kit.png"},"playedGames":38,"wins":16,"draws":9,"loses":13,"goalsFor":54,"goalsAgainst":46,"goalDifference":8,"points":57,"form":"L,L,W,W,L"},{"position":9,"team":{"id":"MZFZnvX4","name":"Torino","logo":"https://raw.githubusercontent.com/mzafram2001/zeus-src/main/static/logos/MZFZnvX4_logo.png","kit":"https://raw.githubusercontent.com/mzafram2001/zeus-src/main/static/kits/MZFZnvX4_kit.png"},"playedGames":38,"wins":13,"draws":15,"loses":10,"goalsFor":54,"goalsAgainst":46,"goalDifference":8,"points":54,"form":"W,W,D,L,L"},{"position":10,"team":{"id":"nJbCGx2U","name":"Sampdoria","logo":"https://raw.githubusercontent.com/mzafram2001/zeus-src/main/static/logos/nJbCGx2U_logo.png","kit":"https://raw.githubusercontent.com/mzafram2001/zeus-src/main/static/kits/nJbCGx2U_kit.png"},"playedGames":38,"wins":16,"draws":6,"loses":16,"goalsFor":56,"goalsAgainst":60,"goalDifference":-4,"points":54,"form":"L,L,L,W,L"},{"position":11,"team":{"id":"QDdvI0zl","name":"Sassuolo","logo":"https://raw.githubusercontent.com/mzafram2001/zeus-src/main/static/logos/QDdvI0zl_logo.png","kit":"https://raw.githubusercontent.com/mzafram2001/zeus-src/main/static/kits/QDdvI0zl_kit.png"},"playedGames":38,"wins":11,"draws":10,"loses":17,"goalsFor":29,"goalsAgainst":59,"goalDifference":-30,"points":43,"form":"L,W,W,L,W"},{"position":12,"team":{"id":"d0PJxeie","name":"Genoa","logo":"https://raw.githubusercontent.com/mzafram2001/zeus-src/main/static/logos/d0PJxeie_logo.png","kit":"https://raw.githubusercontent.com/mzafram2001/zeus-src/main/static/kits/d0PJxeie_kit.png"},"playedGames":38,"wins":11,"draws":8,"loses":19,"goalsFor":33,"goalsAgainst":43,"goalDifference":-10,"points":41,"form":"L,L,L,L,W"},{"position":13,"team":{"id":"xdTJgGvo","name":"Chievo","logo":"https://raw.githubusercontent.com/mzafram2001/zeus-src/main/static/logos/xdTJgGvo_logo.png","kit":"https://raw.githubusercontent.com/mzafram2001/zeus-src/main/static/kits/xdTJgGvo_kit.png"},"playedGames":38,"wins":10,"draws":10,"loses":18,"goalsFor":36,"goalsAgainst":59,"goalDifference":-23,"points":40,"form":"W,W,W,L,L"},{"position":14,"team":{"id":"rXw8YKDE","name":"Udinese","logo":"https://raw.githubusercontent.com/mzafram2001/zeus-src/main/static/logos/rXw8YKDE_logo.png","kit":"https://raw.githubusercontent.com/mzafram2001/zeus-src/main/static/kits/rXw8YKDE_kit.png"},"playedGames":38,"wins":12,"draws":4,"loses":22,"goalsFor":48,"goalsAgainst":63,"goalDifference":-15,"points":40,"form":"W,W,L,D,L"},{"position":15,"team":{"id":"0M9xNN8N","name":"Bologna","logo":"https://raw.githubusercontent.com/mzafram2001/zeus-src/main/static/logos/0M9xNN8N_logo.png","kit":"https://raw.githubusercontent.com/mzafram2001/zeus-src/main/static/kits/0M9xNN8N_kit.png"},"playedGames":38,"wins":11,"draws":6,"loses":21,"goalsFor":40,"goalsAgainst":52,"goalDifference":-12,"points":39,"form":"L,L,L,L,D"},{"position":16,"team":{"id":"SCGVmKHb","name":"Cagliari","logo":"https://raw.githubusercontent.com/mzafram2001/zeus-src/main/static/logos/SCGVmKHb_logo.png","kit":"https://raw.githubusercontent.com/mzafram2001/zeus-src/main/static/kits/SCGVmKHb_kit.png"},"playedGames":38,"wins":11,"draws":6,"loses":21,"goalsFor":33,"goalsAgainst":61,"goalDifference":-28,"points":39,"form":"W,W,L,L,D"},{"position":17,"team":{"id":"SCurW5ZE","name":"Spal","logo":"https://raw.githubusercontent.com/mzafram2001/zeus-src/main/static/logos/SCurW5ZE_logo.png","kit":"https://raw.githubusercontent.com/mzafram2001/zeus-src/main/static/kits/SCurW5ZE_kit.png"},"playedGames":38,"wins":8,"draws":14,"loses":16,"goalsFor":39,"goalsAgainst":59,"goalDifference":-20,"points":38,"form":"W,L,W,W,L"},{"position":18,"team":{"id":"d8H0SxkJ","name":"Crotone","logo":"https://raw.githubusercontent.com/mzafram2001/zeus-src/main/static/logos/d8H0SxkJ_logo.png","kit":"https://raw.githubusercontent.com/mzafram2001/zeus-src/main/static/kits/d8H0SxkJ_kit.png"},"playedGames":38,"wins":9,"draws":8,"loses":21,"goalsFor":40,"goalsAgainst":66,"goalDifference":-26,"points":35,"form":"L,D,L,W,W"},{"position":19,"team":{"id":"rJVAIaHo","name":"Verona","logo":"https://raw.githubusercontent.com/mzafram2001/zeus-src/main/static/logos/rJVAIaHo_logo.png","kit":"https://raw.githubusercontent.com/mzafram2001/zeus-src/main/static/kits/rJVAIaHo_kit.png"},"playedGames":38,"wins":7,"draws":4,"loses":27,"goalsFor":30,"goalsAgainst":78,"goalDifference":-48,"points":25,"form":"L,L,L,L,L"},{"position":20,"team":{"id":"rZhSxrse","name":"Benevento","logo":"https://raw.githubusercontent.com/mzafram2001/zeus-src/main/static/logos/rZhSxrse_logo.png","kit":"https://raw.githubusercontent.com/mzafram2001/zeus-src/main/static/kits/rZhSxrse_kit.png"},"playedGames":38,"wins":6,"draws":3,"loses":29,"goalsFor":33,"goalsAgainst":84,"goalDifference":-51,"points":21,"form":"L,W,L,D,W"}]}