{"name":"Premier League","area":"ENG","yearStart":2022,"yearEnd":2023,"standings":[{"position":1,"team":{"id":"hA1Zm19f","name":"Arsenal","logo":"https://raw.githubusercontent.com/mzafram2001/zeus-src/main/static/teams/hA1Zm19f.svg"},"playedGames":30,"wins":23,"draws":4,"loses":3,"goalsFor":72,"goalsAgainst":29,"goalDifference":43,"points":73,"form":"D,W,W,W,W"},{"position":2,"team":{"id":"Wtn9Stg0","name":"Manchester City","logo":"https://raw.githubusercontent.com/mzafram2001/zeus-src/main/static/teams/Wtn9Stg0.svg"},"playedGames":30,"wins":22,"draws":4,"loses":4,"goalsFor":78,"goalsAgainst":28,"goalDifference":50,"points":70,"form":"W,W,W,W,W"},{"position":3,"team":{"id":"p6ahwuwJ","name":"Newcastle United","logo":"https://raw.githubusercontent.com/mzafram2001/zeus-src/main/static/teams/p6ahwuwJ.svg"},"playedGames":30,"wins":15,"draws":11,"loses":4,"goalsFor":48,"goalsAgainst":24,"goalDifference":24,"points":56,"form":"L,W,W,W,W"},{"position":4,"team":{"id":"ppjDR086","name":"Manchester United","logo":"https://raw.githubusercontent.com/mzafram2001/zeus-src/main/static/teams/ppjDR086.svg"},"playedGames":29,"wins":17,"draws":5,"loses":7,"goalsFor":44,"goalsAgainst":37,"goalDifference":7,"points":56,"form":"W,W,L,D,L"},{"position":5,"team":{"id":"UDg08Ohm","name":"Tottenham Hotspur","logo":"https://raw.githubusercontent.com/mzafram2001/zeus-src/main/static/teams/UDg08Ohm.svg"},"playedGames":31,"wins":16,"draws":5,"loses":10,"goalsFor":57,"goalsAgainst":45,"goalDifference":12,"points":53,"form":"L,W,D,D,W"},{"position":6,"team":{"id":"W00wmLO0","name":"Aston Villa","logo":"https://raw.githubusercontent.com/mzafram2001/zeus-src/main/static/teams/W00wmLO0.svg"},"playedGames":31,"wins":15,"draws":5,"loses":11,"goalsFor":44,"goalsAgainst":40,"goalDifference":4,"points":50,"form":"W,W,W,W,W"},{"position":7,"team":{"id":"2XrRecc3","name":"Brighton","logo":"https://raw.githubusercontent.com/mzafram2001/zeus-src/main/static/teams/2XrRecc3.svg"},"playedGames":29,"wins":14,"draws":7,"loses":8,"goalsFor":54,"goalsAgainst":37,"goalDifference":17,"points":49,"form":"W,L,W,D,W"},{"position":8,"team":{"id":"lId4TMwf","name":"Liverpool","logo":"https://raw.githubusercontent.com/mzafram2001/zeus-src/main/static/teams/lId4TMwf.svg"},"playedGames":29,"wins":12,"draws":8,"loses":9,"goalsFor":50,"goalsAgainst":35,"goalDifference":15,"points":44,"form":"D,D,L,L,W"},{"position":9,"team":{"id":"xYe7DwID","name":"Brentford","logo":"https://raw.githubusercontent.com/mzafram2001/zeus-src/main/static/teams/xYe7DwID.svg"},"playedGames":31,"wins":10,"draws":13,"loses":8,"goalsFor":47,"goalsAgainst":42,"goalDifference":5,"points":43,"form":"L,L,L,D,D"},{"position":10,"team":{"id":"69ZiU2Om","name":"Fulham","logo":"https://raw.githubusercontent.com/mzafram2001/zeus-src/main/static/teams/69ZiU2Om.svg"},"playedGames":30,"wins":12,"draws":6,"loses":12,"goalsFor":42,"goalsAgainst":41,"goalDifference":1,"points":42,"form":"W,L,L,L,L"},{"position":11,"team":{"id":"4fGZN2oK","name":"Chelsea","logo":"https://raw.githubusercontent.com/mzafram2001/zeus-src/main/static/teams/4fGZN2oK.svg"},"playedGames":31,"wins":10,"draws":9,"loses":12,"goalsFor":30,"goalsAgainst":33,"goalDifference":-3,"points":39,"form":"L,L,D,L,D"},{"position":12,"team":{"id":"AovF1Mia","name":"Crystal Palace","logo":"https://raw.githubusercontent.com/mzafram2001/zeus-src/main/static/teams/AovF1Mia.svg"},"playedGames":31,"wins":9,"draws":9,"loses":13,"goalsFor":31,"goalsAgainst":40,"goalDifference":-9,"points":36,"form":"W,W,W,L,L"},{"position":13,"team":{"id":"j3Azpf5d","name":"Wolverhampton Wanderers","logo":"https://raw.githubusercontent.com/mzafram2001/zeus-src/main/static/teams/j3Azpf5d.svg"},"playedGames":31,"wins":9,"draws":7,"loses":15,"goalsFor":26,"goalsAgainst":42,"goalDifference":-16,"points":34,"form":"W,W,D,L,L"},{"position":14,"team":{"id":"OtpNdwrc","name":"Athletic Bournemouth","logo":"https://raw.githubusercontent.com/mzafram2001/zeus-src/main/static/teams/OtpNdwrc.svg"},"playedGames":31,"wins":9,"draws":6,"loses":16,"goalsFor":31,"goalsAgainst":59,"goalDifference":-28,"points":33,"form":"W,W,L,W,L"},{"position":15,"team":{"id":"Cxq57r8g","name":"West Ham United","logo":"https://raw.githubusercontent.com/mzafram2001/zeus-src/main/static/teams/Cxq57r8g.svg"},"playedGames":29,"wins":8,"draws":6,"loses":15,"goalsFor":27,"goalsAgainst":39,"goalDifference":-12,"points":30,"form":"W,L,W,D,L"},{"position":16,"team":{"id":"tUxUbLR2","name":"Leeds United","logo":"https://raw.githubusercontent.com/mzafram2001/zeus-src/main/static/teams/tUxUbLR2.svg"},"playedGames":30,"wins":7,"draws":8,"loses":15,"goalsFor":39,"goalsAgainst":54,"goalDifference":-15,"points":29,"form":"L,W,L,W,D"},{"position":17,"team":{"id":"KluSTr9s","name":"Everton","logo":"https://raw.githubusercontent.com/mzafram2001/zeus-src/main/static/teams/KluSTr9s.svg"},"playedGames":31,"wins":6,"draws":9,"loses":16,"goalsFor":24,"goalsAgainst":46,"goalDifference":-22,"points":27,"form":"L,L,D,D,W"},{"position":18,"team":{"id":"UsushcZr","name":"Nottingham Forest","logo":"https://raw.githubusercontent.com/mzafram2001/zeus-src/main/static/teams/UsushcZr.svg"},"playedGames":30,"wins":6,"draws":9,"loses":15,"goalsFor":24,"goalsAgainst":54,"goalDifference":-30,"points":27,"form":"L,L,D,L,L"},{"position":19,"team":{"id":"KrrdAMyI","name":"Leicester City","logo":"https://raw.githubusercontent.com/mzafram2001/zeus-src/main/static/teams/KrrdAMyI.svg"},"playedGames":31,"wins":7,"draws":4,"loses":20,"goalsFor":41,"goalsAgainst":55,"goalDifference":-14,"points":25,"form":"L,L,L,L,D"},{"position":20,"team":{"id":"WdKOwxDM","name":"Southampton","logo":"https://raw.githubusercontent.com/mzafram2001/zeus-src/main/static/teams/WdKOwxDM.svg"},"playedGames":31,"wins":6,"draws":5,"loses":20,"goalsFor":24,"goalsAgainst":53,"goalDifference":-29,"points":23,"form":"L,L,L,D,L"}]}